aaron_sql_mcp_for_intern/__init__.py
aaron_sql_mcp_for_intern-0.1.0.dist-info/WHEEL
aaron_sql_mcp_for_intern-0.1.0.dist-info/entry_points.txt
aaron_sql_mcp_for_intern-0.1.0.dist-info/METADATA
aaron_sql_mcp_for_intern-0.1.0.dist-info/RECORD
