Metadata-Version: 2.3
Name: aaron-sql-mcp-for-intern
Version: 0.1.0
Summary: Add your description here
Author: aaronuslife
Author-email: aaronuslife <aaronuslife@gmail.com>
Requires-Dist: mcp[cli]>=1.20.0
Requires-Python: >=3.12
